bili_eta/.env.prod
bili_eta/__init__.py
bili_eta/__main__.py
bili_eta/bot.py
bili_eta/plugins/eta/Command.py
bili_eta/plugins/eta/Src/BiliApi.py
bili_eta/plugins/eta/Src/BotSwitchManager.py
bili_eta/plugins/eta/Src/DataManager/CookieManager.py
bili_eta/plugins/eta/Src/DataManager/FollowManager.py
bili_eta/plugins/eta/Src/DataManager/SwitchManager.py
bili_eta/plugins/eta/Src/DataManager/__init__.py
bili_eta/plugins/eta/Src/DynPusher.py
bili_eta/plugins/eta/Src/DynamicManager.py
bili_eta/plugins/eta/Src/FollowListManager.py
bili_eta/plugins/eta/Src/LivePusher.py
bili_eta/plugins/eta/Src/MessageManager.py
bili_eta/plugins/eta/Src/Other.py
bili_eta/plugins/eta/Src/SignIn.py
bili_eta/plugins/eta/Src/Static/HanaMinA.ttf
bili_eta/plugins/eta/Src/Static/help.png
bili_eta/plugins/eta/Src/StatuChecker.py
bili_eta/plugins/eta/Src/SubManager.py
bili_eta/plugins/eta/Src/__init__.py
bili_eta/plugins/eta/__init__.py
bili_eta/plugins/eta/tasks.py
bili_eta-0.3.4.dist-info/METADATA
bili_eta-0.3.4.dist-info/WHEEL
bili_eta-0.3.4.dist-info/entry_points.txt
bili_eta-0.3.4.dist-info/RECORD
