Metadata-Version: 2.1
Name: bili-eta
Version: 0.3.4
Summary: 
Author: Polyisoprene
Author-email: lzxder@outlook.com
Requires-Python: >=3.8,<4.0
Classifier: Programming Language :: Python :: 3
Classifier: Programming Language :: Python :: 3.8
Classifier: Programming Language :: Python :: 3.9
Classifier: Programming Language :: Python :: 3.10
Classifier: Programming Language :: Python :: 3.11
Requires-Dist: click (>=8.1.6,<9.0.0)
Requires-Dist: dynrender-skia (>=0.1.6,<0.2.0)
Requires-Dist: nonebot-adapter-onebot (>=2.2.3,<3.0.0)
Requires-Dist: nonebot-plugin-apscheduler (>=0.3.0,<0.4.0)
Requires-Dist: nonebot-plugin-guild-patch (>=0.2.3,<0.3.0)
Requires-Dist: nonebot2[fastapi] (>=2.0.1,<3.0.0)
Requires-Dist: python-dotenv (>=1.0.0,<2.0.0)
